README.rst
setup.py
pyerarchy/__init__.py
pyerarchy/modulenode.py
pyerarchy.egg-info/PKG-INFO
pyerarchy.egg-info/SOURCES.txt
pyerarchy.egg-info/dependency_links.txt
pyerarchy.egg-info/requires.txt
pyerarchy.egg-info/top_level.txt
pyerarchy/core/__init__.py
pyerarchy/core/node.py
pyerarchy/ex/__init__.py
tests/__init__.py
tests/core/__init__.py
tests/core/test_modulenode.py
tests/core/test_node.py