Metadata-Version: 1.1
Name: pyerarchy
Version: 0.1
Summary: Access directories like objects
Home-page: git@github.com:n9code/pyerarchy.git
Author: Bagrat Aznauryan
Author-email: bagrat@aznauryan.org
License: MIT
Download-URL: git@github.com:n9code/pyerarchy.git
Keywords: directory file object
Platform: UNKNOWN
Classifier: License :: OSI Approved :: MIT License
Classifier: Intended Audience :: Developers
Classifier: Natural Language :: English
Classifier: Programming Language :: Python
Classifier: Programming Language :: Python :: 2
Classifier: Programming Language :: Python :: 3
Classifier: Operating System :: POSIX
Classifier: Operating System :: POSIX :: Linux
Classifier: Operating System :: MacOS
Classifier: Operating System :: Microsoft :: Windows
Classifier: Topic :: Software Development :: Libraries :: Python Modules
